plone.app.querystring-2.1.4-py3.13-nspkg.pth
plone/app/querystring/__init__.py
plone/app/querystring/configure.zcml
plone/app/querystring/hiddenprofiles.py
plone/app/querystring/interfaces.py
plone/app/querystring/profiles.zcml
plone/app/querystring/querybuilder.py
plone/app/querystring/querymodifiers.py
plone/app/querystring/queryparser.py
plone/app/querystring/registryreader.py
plone/app/querystring/results.pt
plone/app/querystring/testing.py
plone/app/querystring/upgrades.py
plone/app/querystring/upgrades.zcml
plone/app/querystring/vocabularies.py
plone/app/querystring/indexmodifiers/__init__.py
plone/app/querystring/indexmodifiers/configure.zcml
plone/app/querystring/indexmodifiers/query_index_modifiers.py
plone/app/querystring/profiles/default/metadata.xml
plone/app/querystring/profiles/default/registry.xml
plone/app/querystring/profiles/upgrades/to_10/registry.xml
plone/app/querystring/profiles/upgrades/to_11/registry.xml
plone/app/querystring/profiles/upgrades/to_14/registry.xml
plone/app/querystring/profiles/upgrades/to_3/registry.xml
plone/app/querystring/profiles/upgrades/to_5/registry.xml
plone/app/querystring/profiles/upgrades/to_6/registry.xml
plone/app/querystring/profiles/upgrades/to_7/registry.xml
plone/app/querystring/profiles/upgrades/to_8/registry.xml
plone/app/querystring/profiles/upgrades/to_9/registry.xml
plone/app/querystring/tests/__init__.py
plone/app/querystring/tests/configure.zcml
plone/app/querystring/tests/index_testmodifier.py
plone/app/querystring/tests/registry_minimal_correct.xml
plone/app/querystring/tests/registry_test_missing_operator.xml
plone/app/querystring/tests/registry_test_vocabulary.xml
plone/app/querystring/tests/registry_testdata.py
plone/app/querystring/tests/testIndexmodifiers.py
plone/app/querystring/tests/testQueryBuilder.py
plone/app/querystring/tests/testQueryBuilderModifiers.py
plone/app/querystring/tests/testQueryParser.py
plone/app/querystring/tests/testRegistryIntegration.py
plone_app_querystring-2.1.4.dist-info/METADATA
plone_app_querystring-2.1.4.dist-info/WHEEL
plone_app_querystring-2.1.4.dist-info/entry_points.txt
plone_app_querystring-2.1.4.dist-info/namespace_packages.txt
plone_app_querystring-2.1.4.dist-info/top_level.txt
plone_app_querystring-2.1.4.dist-info/RECORD
