Metadata-Version: 2.4
Name: plone.app.querystring
Version: 2.1.4
Summary: A queryparser, querybuilder and extra helper tools, to parse stored queries to actual results, used in new style Plone collections
Home-page: https://github.com/plone/plone.app.querystring
Author: Plone Foundation
Author-email: plone-developers@lists.sourceforge.net
License: GPL version 2
Keywords: collection queries
Classifier: Development Status :: 5 - Production/Stable
Classifier: Framework :: Plone
Classifier: Framework :: Plone :: 6.0
Classifier: Framework :: Plone :: Core
Classifier: License :: OSI Approved :: GNU General Public License v2 (GPLv2)
Classifier: Programming Language :: Python
Classifier: Programming Language :: Python :: 3.8
Classifier: Programming Language :: Python :: 3.9
Classifier: Programming Language :: Python :: 3.10
Classifier: Programming Language :: Python :: 3.11
Requires-Python: >=3.8
Requires-Dist: setuptools
Requires-Dist: plone.app.contentlisting
Requires-Dist: plone.app.registry>=1.1
Requires-Dist: plone.app.vocabularies
Requires-Dist: plone.base
Requires-Dist: plone.batching
Requires-Dist: plone.i18n
Requires-Dist: plone.registry
Requires-Dist: plone.uuid
Requires-Dist: Products.GenericSetup
Requires-Dist: Products.ZCatalog
Requires-Dist: python-dateutil
Requires-Dist: Zope
Requires-Dist: zope.dottedname
Requires-Dist: zope.globalrequest
Provides-Extra: test
Requires-Dist: plone.app.testing; extra == "test"
Requires-Dist: plone.app.contenttypes[test]; extra == "test"
Dynamic: author
Dynamic: author-email
Dynamic: classifier
Dynamic: description
Dynamic: home-page
Dynamic: keywords
Dynamic: license
Dynamic: provides-extra
Dynamic: requires-dist
Dynamic: requires-python
Dynamic: summary
